rapidpro_pull-1.0.3.dist-info/DESCRIPTION.rst
rapidpro_pull-1.0.3.dist-info/METADATA
rapidpro_pull-1.0.3.dist-info/RECORD
rapidpro_pull-1.0.3.dist-info/WHEEL
rapidpro_pull-1.0.3.dist-info/entry_points.txt
rapidpro_pull-1.0.3.dist-info/metadata.json
rapidpro_pull-1.0.3.dist-info/top_level.txt
rapidpropull/__init__.py
rapidpropull/cache.py
rapidpropull/cli.py
rapidpropull/download.py
