Metadata-Version: 2.0
Name: rapidpro-pull
Version: 1.0.3
Summary: An open-source tool to pull and cache data from RapidPro servers.
Home-page: https://github.com/system7-open-source/rapidpro-pull
Author: Tomasz J. Kotarba
Author-email: tomasz@kotarba.net
License: GPLv3+
Keywords: rapidpro
Platform: UNKNOWN
Classifier: Development Status :: 5 - Production/Stable
Classifier: Intended Audience :: End Users/Desktop
Classifier: Intended Audience :: System Administrators
Classifier: Topic :: Desktop Environment
Classifier: Topic :: Internet
Classifier: Topic :: Utilities
Classifier: Operating System :: OS Independent
Classifier: License :: OSI Approved :: GNU General Public License v3 or later (GPLv3+)
Classifier: Environment :: Console
Classifier: Programming Language :: Python :: 2
Classifier: Programming Language :: Python :: 2.7
Requires-Python: >=2.7,!=3.*
Requires-Dist: docopt (>=0.6,<1)
Requires-Dist: rapidpro-python (<3,>=2.1.1)
Requires-Dist: sqlalchemy (>=1.1.3,<2)
Provides-Extra: development
Requires-Dist: PyHamcrest (>=1.9,<2); extra == 'development'
Requires-Dist: behave (>=1.2.5,<2); extra == 'development'
Requires-Dist: iocapture (>=0.1.2,<1); extra == 'development'
Requires-Dist: mock (<3,>=2); extra == 'development'
Requires-Dist: pretenders (>=1.4.2,<2); extra == 'development'
Requires-Dist: pytest (>=3,<4); extra == 'development'
Requires-Dist: pytest-cov (>=2.4,<3); extra == 'development'
Requires-Dist: pytz (>=2016.7); extra == 'development'
Requires-Dist: tox-travis; extra == 'development'
